orbvis/__init__.py
orbvis/main.py
orbvis/band/__init__.py
orbvis/band/parser.py
orbvis/band/plotter.py
orbvis/band/utils.py
orbvis/dos/__init__.py
orbvis/dos/parser.py
orbvis/dos/plotter.py
orbvis/dos/utils.py
orbvis-1.0.2.dist-info/licenses/LICENSE
orbvis-1.0.2.dist-info/METADATA
orbvis-1.0.2.dist-info/WHEEL
orbvis-1.0.2.dist-info/entry_points.txt
orbvis-1.0.2.dist-info/top_level.txt
orbvis-1.0.2.dist-info/RECORD
