Metadata-Version: 2.4
Name: orbvis
Version: 1.0.2
Summary: A python package to vizualize orbital-resolved band structure and DOS
Author: Taradutt Pattnaik
License: MIT
Project-URL: Repository, https://github.com/staradutt/orbvis
Project-URL: Documentation, https://github.com/staradutt/orbvis/tree/main/docs
Project-URL: Examples, https://github.com/staradutt/orbvis/tree/main/examples
Project-URL: Issues, https://github.com/staradutt/orbvis/issues
Requires-Python: >=3.8
License-File: LICENSE
Requires-Dist: numpy>=1.24
Requires-Dist: scipy>=1.10
Requires-Dist: distinctipy>=1.3
Requires-Dist: matplotlib>=3.6
Dynamic: license-file
